{
  "expeditionSkills": {
    "darkteo": [
      {
        "setName": "종결세팅",
        "teams": [
          {
            "teamName": "1팀",
            "skills1": {
              "tag": "2방컷",
              "sequence": [
                "rachel2.png",
                "bisket1.png",
                "pascal2.png",
                "pascal1.png",
                { "image": "pascal2.png", "label": "테오 불사 진입(딜부족 시 미호 사용)" },
                { "image": "bisket2.png", "label": "태오 불사 해제" }
              ]
            },
            "skills2": {
              "tag": "3방컷",
              "sequence": [
              "rachel2.png",
                "bisket1.png",
                "pascal2.png",
                "pascal1.png",
                "pascal2.png",
                "miho1.png",
                "pascal1.png",
                { "image": "pascal2.png", "label": "테오 불사 진입(딜부족 시 미호 사용)" },
                { "image": "bisket2.png", "label": "태오 불사 해제" }
              ]
            }
          },
          {
            "teamName": "2팀",
            "skills": {
               "sequence": [
              "espada1.png",
              "lina2.png",
              "yuri1.png",
              "yuri2.png",
              "dage1.png",
                 "lina1.png",
              "espada1.png",
           
              "yuri1.png","dage2.png","yuri2.png","lina2.png","dage1.png","yuri1.png"
                ] }
          }
        ]
      }
    ],
    "darkyeonhee": [
      {
        "setName": "안전세팅",
        "teams": [
          {
            "teamName": "1팀",
            "skills": {
               "sequence": [
              "lina2.png",
              "chloe2.png",
              "vanessa1.png",
              "luri2.png",
              "luri1.png",
              
              "Yeonhee1.png"
      
            ]}
          },
          {
            "teamName": "2팀",
          "skills": {
               "sequence": [
              "bisket1.png",
              "miho1.png",
              "orly1.png",
              "dage2.png",
              "miho2.png",
              "juri2.png",
              "orly2.png",
              "miho1.png",
              "orly1.png","bisket1.png","juri1.png","miho2.png","dage2.png","miho1.png"
            ]}
          }
        ]
      }
    ],
     "darkcarma": [
      {
        "setName": "종결세팅",
        "teams": [
          {
            "teamName": "1팀(32턴)",
        "skills": {
               "sequence": [
              "poongyeon1.png",
              "taka1.png",
              "ace2.png",
              "taka2.png",
              "poongyeon2.png",
              
              "poongyeon1.png",
                "pie1.png",
                  "taka1.png",
                     "taka2.png"
      
            ]}
          },
          {
            "teamName": "2팀",
         "skills": {
               "sequence": [
              "bisket1.png",
              "rachel2.png",
              "bidam1.png",
              "bidam2.png",
              "lina2.png",
              "rachel1.png",
              "bidam1.png",
              "rachel2.png","bidam2.png",  { "image": "bisket1.png", "label": "아마 이때 딜스킬쓰는게 더 좋을듯" }
            ]}
          }
        ]
      }
    ],
      "darkkile": [
      {
        "setName": "종결세팅",
        "teams": [
          {
            "teamName": "1팀(36턴)",
         "skills": {
               "sequence": [
              "jupi1.png",
              "pie1.png",
              "jupi2.png",
              "jupi1.png",
              "dellons2.png",
              
              "yui1.png",
                "pie2.png",
                  "jupi2.png",
                     "jupi1.png",
                     "ace1.png"
      
            ]}
          },
          {
            "teamName": "2팀",
      "skills": {
               "sequence": [
              "bisket1.png",
              "rachel2.png",
              "sein1.png",
              "lina2.png",
              "zick2.png",
              "sein1.png",
              "lina1.png",
              "rachel2.png",
              "sein1.png"
            ]}
          }
        ]
      },
      {
        "setName": "안전세팅",
        "teams": [
          {
            "teamName": "1팀",
         "skills": {
               "sequence": [
             "bisket1.png",
              "rachel2.png",
              "sein1.png",
             
              "zick2.png",
              "yui1.png",
              "sein1.png",
              "zick1.png",
              "rachel2.png",
              "sein1.png",
              "zick2.png"
      
            ]}
          },
          {
            "teamName": "2팀",
      "skills": {
               "sequence": [
              "jupi1.png",
              "lina2.png",
              "jupi2.png",
              "jupi1.png",
              "lina1.png",
              "ace2.png",
              "jupi2.png",
              "dellons2.png",
              "jupi1.png",
              "pie2.png"
            ]}
          }
        ]
      }
    ],
      "bosss": [{
        "setName": "종결 빌드",
        "teams": [
          {
            "teamName": "1팀(20)",
         "skills": {
               "sequence": [
                "chancellor1.png",
              "bisket1.png",
              "miho1.png",
             
              "pascal2.png",
              
              "pascal1.png",
                "pascal2.png"
                  
      
            ]}
          },
          {
            "teamName": "2팀",
      "skills": {
               "sequence": [
              "rachel2.png",
              "sein1.png",
              "lina1.png",
              "zick1.png",
              "sein1.png",
              "zick2.png",
             
             
              "rachel2.png","sein1.png","zick1.png","lina1.png","sein1.png","zick2.png"
            ]}
          }
        ]
      },
      {
        "setName": "안전 빌드",
        "teams": [
          {
            "teamName": "1팀(20)",
         "skills": {
               "sequence": [
              "bisket1.png",
              "miho1.png",
              "lina1.png",
              "lina2.png",
              "pascal2.png",
              
              "pascal1.png",
                "pascal2.png"
                  
      
            ]}
          },
          {
            "teamName": "2팀",
      "skills": {
               "sequence": [
              "rachel2.png",
              "sein1.png",
              "elise2.png",
              "zick2.png",
              "sein1.png",
                 "elise1.png",
              "zick1.png",
              
              "sein1.png",
              "rachel2.png","elise2.png","sein1.png","zick2.png"
            ]}
          }
        ]
      }
    ]
  }
}
