{
  "categories": {
    "공덱": {
     "desc": "속공 중요",
      "teams": [
        {
          "teamId": 1,
          "name": "파이 공덱",
          "heroes": [
            { "name": "엘리시아", "image": "elisia.png","preset":"총력전","note":"2초부터 사용가능"},
            { "name": "카구라", "image": "cagura.png","preset":"총력전" },
              { "name": "카일", "image": "kyle.png","preset":"총력전","note":"권불세공>불>권" },
            { "name": "콜트", "image": "colt.png","preset":"총력전" },
           { "name": "파이", "image": "pie.png","preset":"총력전" }
          ],
        "skillOrders": [
  {
    "title": "보편적",
    "sequence": ["colt2.png", "kyle2.png", "elisia2.png"]
  },
  {
    "title": "보편적",
    "sequence": ["kyle2.png", "elisia2.png", "colt2.png"]
  },
  {
    "title": "보편적",
    "sequence": ["kyle2.png", "kyle1.png", "elisia2.png"]
  }
  
],
"note":"속공460"
          
        }
        
       
      ]
    },
    "마덱": {
      "desc": "속공 중요",
      "teams": [
        {
          "teamId": 1,
          "name": "플라튼 마덱",
          "heroes": [
             { "name": "쥬리", "image": "juri.png","preset":"프리셋1(속공)"},
           
            { "name": "아멜리아", "image": "amelia.png","preset":""},
              { "name": "플라튼", "image": "platon.png","preset":"프리셋1(탱)"},
            { "name": "린", "image": "rin.png","preset":"프리셋1(속공)" },
            { "name": "멜키르", "image": "melkir.png","preset":"프리셋2(속공)" }
          ],
          "skillOrders": [
  {
    "title": "보편적",
    "sequence": ["melkir1.png", "melkir2.png", "amelia2.png"]
  }
 
],
"note":"스킬순서는 승률 더 잘나온느걸로"
        },
        {
          "teamId": 2,
          "name": "오를리 마덱",
          "heroes": [
            { "name": "유신", "image": "Yushin.png","preset":"" },
            { "name": "바네사", "image": "vanessa.png" ,"preset":"프리셋2(속공)"},
               { "name": "오를리", "image": "orly.png","preset":"프리셋2(속공)" },
            { "name": "연희", "image": "Yeonhee.png","preset":"프리셋2(내실)" },
          
              { "name": "실베스타", "image": "silvesta.png","preset":"프리셋1(내실)" }
          ],
          "skillOrder": ["Yeonhee2.png", "orly2.png", "silvesta2.png"],
          "note":"오를리 치확20%만큼 연희,실베스타 속공 챙겨주기"
        }
        
      ]
    },
     "방덱": {
      "desc": "체급 중요(속공x)",
      "teams": [
        {
          "teamId": 1,
          "name": "카르마 방덱",
          "heroes": [
             { "name": "엘리스", "image": "elise.png","preset":""},
             { "name": "루디", "image": "rudy.png","preset":"프리셋1(범용)"},
            { "name": "카르마", "image": "carma.png","preset":"프리셋1(범용)"},
            { "name": "제이브", "image": "jave.png" ,"preset":"프리셋1(범용)"},
            { "name": "리나", "image": "lina.png","preset":"" }
          ],
          "skillOrders": [
  {
    "title": "보편적1",
    "sequence": ["rudy2.png", "carma2.png", "elise1.png"]
  }
 
   
],
"note":"스킬순서는 승률 더 잘나온느걸로"
        }
        
        
      ]
    },
     "즉사덱": {
      "desc": "체급 중요(속공x)",
      "teams": [
        {
          "teamId": 1,
          "name": "즉사 방덱",
          "heroes": [
             { "name": "로지", "image": "lozy.png","preset":""},
             { "name": "크리스", "image": "chris.png","preset":""},
            { "name": "니아", "image": "nia.png","preset":""},
            { "name": "녹스", "image": "nox.png","preset":"" },
            { "name": "카린", "image": "carin.png","preset":"","note":"아킬라 대체가능" }
          ],
          "skillOrders": [
  {
    "title": "보편적1",
    "sequence": ["nia2.png", "chris2.png", "lozy1.png"]
  }
 
   
],
"note":"다 속공 짬통으로 주기"
        }
        
        
      ]
    }
  }
}
